dconnect/__init__.py
dconnect/dconnect.py
dconnect/__pycache__/__init__.cpython-37.pyc
dconnect/__pycache__/dconnect.cpython-37.pyc
dconnect-1.0.1.dist-info/LICENSE.txt
dconnect-1.0.1.dist-info/METADATA
dconnect-1.0.1.dist-info/WHEEL
dconnect-1.0.1.dist-info/top_level.txt
dconnect-1.0.1.dist-info/RECORD
