Metadata-Version: 2.1
Name: dconnect
Version: 1.0.1
Summary: Power your data connections with python and queries with dconnect
Home-page: https://github.com/nit567esh/dconnect
Author: Nitesh Kumar
Author-email: nit567esh@gmail.com
License: UNKNOWN
Platform: UNKNOWN
Requires-Dist: pandas
